_pymarian.cpython-311-x86_64-linux-gnu.so
pymarian/__init__.py
pymarian/__main__.py
pymarian/_version.py
pymarian/defaults.py
pymarian/eval.py
pymarian/mtapi_server.py
pymarian/qtdemo.py
pymarian/utils.py
pymarian/pypdl/__init__.py
pymarian/pypdl/downloader.py
pymarian/pypdl/main.py
pymarian/pypdl/utils.py
pymarian-1.12.42.dist-info/METADATA
pymarian-1.12.42.dist-info/WHEEL
pymarian-1.12.42.dist-info/entry_points.txt
pymarian-1.12.42.dist-info/top_level.txt
pymarian-1.12.42.dist-info/RECORD
