Metadata-Version: 2.4
Name: pymarian
Version: 1.12.42
Summary: Pymarian
Author-email: Marian Developers <noreply@email.com>
Classifier: Development Status :: 4 - Beta
Classifier: Programming Language :: Python :: 3 :: Only
Classifier: Programming Language :: Python :: 3.7
Classifier: Programming Language :: Python :: 3.8
Classifier: Programming Language :: Python :: 3.9
Classifier: Programming Language :: Python :: 3.10
Classifier: Programming Language :: Python :: 3.11
Requires-Python: >=3.7
Requires-Dist: portalocker
Requires-Dist: pyyaml
Requires-Dist: tqdm
Requires-Dist: requests
Requires-Dist: huggingface-hub
Provides-Extra: test
Requires-Dist: pytest; extra == "test"
Provides-Extra: demos
Requires-Dist: flask; extra == "demos"
Requires-Dist: sacremoses; extra == "demos"
Requires-Dist: pyqt5; extra == "demos"
